manganova/__init__.py
manganova/__main__.py
manganova/cli/__init__.py
manganova/cli/cli.py
manganova-0.1.0.dist-info/AUTHORS.md
manganova-0.1.0.dist-info/LICENSE
manganova-0.1.0.dist-info/METADATA
manganova-0.1.0.dist-info/WHEEL
manganova-0.1.0.dist-info/entry_points.txt
manganova-0.1.0.dist-info/top_level.txt
manganova-0.1.0.dist-info/RECORD
